MANIFEST.in
README.md
setup.py
SDog.egg-info/PKG-INFO
SDog.egg-info/SOURCES.txt
SDog.egg-info/dependency_links.txt
SDog.egg-info/entry_points.txt
SDog.egg-info/not-zip-safe
SDog.egg-info/requires.txt
SDog.egg-info/top_level.txt
sdog/__init__.py
sdog/example_client.py
sdog/monitor.py
sdog/notifier.py