Metadata-Version: 1.1
Name: SDog
Version: 0.2.1
Summary: SDog
Home-page: http://github.com/shish/sdog
Author: Shish
Author-email: webmaster+sdog@shishnet.org
License: UNKNOWN
Platform: UNKNOWN
Classifier: Programming Language :: Python
